aliyunsdkworkorder/__init__.py
aliyunsdkworkorder/endpoint.py
aliyunsdkworkorder/request/__init__.py
aliyunsdkworkorder/request/v20210610/CloseTicketRequest.py
aliyunsdkworkorder/request/v20210610/CreateTicketRequest.py
aliyunsdkworkorder/request/v20210610/EvaluateTicketRequest.py
aliyunsdkworkorder/request/v20210610/GetAttachmentUploadUrlRequest.py
aliyunsdkworkorder/request/v20210610/GetMqConsumerTagRequest.py
aliyunsdkworkorder/request/v20210610/GetTicketRequest.py
aliyunsdkworkorder/request/v20210610/ListCategoriesRequest.py
aliyunsdkworkorder/request/v20210610/ListProductsRequest.py
aliyunsdkworkorder/request/v20210610/ListTicketNotesRequest.py
aliyunsdkworkorder/request/v20210610/ListTicketsRequest.py
aliyunsdkworkorder/request/v20210610/ReopenTicketRequest.py
aliyunsdkworkorder/request/v20210610/ReplyTicketRequest.py
aliyunsdkworkorder/request/v20210610/__init__.py
aliyun_python_sdk_workorder-3.1.4.dist-info/LICENSE
aliyun_python_sdk_workorder-3.1.4.dist-info/METADATA
aliyun_python_sdk_workorder-3.1.4.dist-info/WHEEL
aliyun_python_sdk_workorder-3.1.4.dist-info/top_level.txt
aliyun_python_sdk_workorder-3.1.4.dist-info/RECORD
